{
  "datetime": "2026-06-13 12:45",
  "pohopolu": {
    "Chinese": "荷蘭園（路邊）",
    "Portuguese": "Conselheiro Ferreira de Almeida (Berma da Estrada)",
    "English": "Conselheiro Ferreira de Almeida (Roadside)",
    "DDTT": "2026061312",
    "CODE": "PO",
    "HE_PM2_5": "4.000",
    "HE_CO": "0.488",
    "HE_SO2": "4.138",
    "HE_NO2": "35.675",
    "HE_O3": "31.500",
    "HE_PM10": "17.000"
  },
  "khhopolu": {
    "Chinese": "九澳（路邊）",
    "Portuguese": "Ka-Hó (Berma da Estrada)",
    "English": "Ka-Hó (Roadside)",
    "DDTT": "2026061312",
    "CODE": "KH",
    "HE_PM2_5": "8.000",
    "HE_CO": "0.557",
    "HE_SO2": "4.897",
    "HE_NO2": "13.631",
    "HE_O3": "49.991",
    "HE_PM10": "16.000"
  },
  "enhopolu": {
    "Chinese": "台山（高密度住宅區）",
    "Portuguese": "Bairro de Tamagnini Barbosa (Alta Densidade Habitacional)",
    "English": "Bairro de Tamagnini Barbosa (High Density Residental Area)",
    "DDTT": "2026061312",
    "CODE": "EN",
    "HE_PM2_5": "6.000",
    "HE_CO": "0.671",
    "HE_SO2": "6.023",
    "HE_NO2": "44.352",
    "HE_O3": "20.100",
    "HE_PM10": "21.000"
  },
  "tchopolu": {
    "Chinese": "氹仔中心區（高密度住宅區）",
    "Portuguese": "Baixa da Taipa (Alta Densidade Habitacional)",
    "English": "Baixa da Taipa (High Density Residental Area)",
    "DDTT": "2026061312",
    "CODE": "TC",
    "HE_PM2_5": "6.000",
    "HE_CO": "0.666",
    "HE_SO2": "5.011",
    "HE_NO2": "19.409",
    "HE_O3": "39.122",
    "HE_PM10": "14.000"
  },
  "tghopolu": {
    "Chinese": "大潭山（一般性）",
    "Portuguese": "Taipa Grande (Ambiental)",
    "English": "Taipa Grande (Ambient)",
    "DDTT": "2026061312",
    "CODE": "TG",
    "HE_PM2_5": "2.000",
    "HE_CO": "0.530",
    "HE_SO2": "1.193",
    "HE_NO2": "17.438",
    "HE_O3": "42.452",
    "HE_PM10": "14.000"
  },
  "cdhopolu": {
    "Chinese": "石排灣（一般性）",
    "Portuguese": "Seac Pai Van (Ambiental)",
    "English": "Seac Pai Van (Ambient)",
    "DDTT": "2026061312",
    "CODE": "CD",
    "HE_PM2_5": "8.000",
    "HE_CO": "0.563",
    "HE_SO2": "3.908",
    "HE_NO2": "7.653",
    "HE_O3": "57.259",
    "HE_PM10": "13.000"
  }
}