{
  "datetime": "2026-06-07 20:45",
  "pohopolu": {
    "Chinese": "荷蘭園（路邊）",
    "Portuguese": "Conselheiro Ferreira de Almeida (Berma da Estrada)",
    "English": "Conselheiro Ferreira de Almeida (Roadside)",
    "DDTT": "2026060720",
    "CODE": "PO",
    "HE_SO2": "3.554",
    "HE_PM10": "21.000",
    "HE_O3": "24.240",
    "HE_PM2_5": "6.000",
    "HE_NO2": "53.942",
    "HE_CO": "0.716"
  },
  "khhopolu": {
    "Chinese": "九澳（路邊）",
    "Portuguese": "Ka-Hó (Berma da Estrada)",
    "English": "Ka-Hó (Roadside)",
    "DDTT": "2026060720",
    "CODE": "KH",
    "HE_SO2": "5.025",
    "HE_PM10": "14.000",
    "HE_O3": "38.803",
    "HE_PM2_5": "6.000",
    "HE_NO2": "12.236",
    "HE_CO": "0.693"
  },
  "enhopolu": {
    "Chinese": "台山（高密度住宅區）",
    "Portuguese": "Bairro de Tamagnini Barbosa (Alta Densidade Habitacional)",
    "English": "Bairro de Tamagnini Barbosa (High Density Residental Area)",
    "DDTT": "2026060720",
    "CODE": "EN",
    "HE_SO2": "5.698",
    "HE_PM10": "14.000",
    "HE_O3": "42.827",
    "HE_PM2_5": "2.000",
    "HE_NO2": "18.488",
    "HE_CO": "0.533"
  },
  "tchopolu": {
    "Chinese": "氹仔中心區（高密度住宅區）",
    "Portuguese": "Baixa da Taipa (Alta Densidade Habitacional)",
    "English": "Baixa da Taipa (High Density Residental Area)",
    "DDTT": "2026060720",
    "CODE": "TC",
    "HE_SO2": "4.348",
    "HE_PM10": "20.000",
    "HE_O3": "42.635",
    "HE_PM2_5": "9.000",
    "HE_NO2": "30.363",
    "HE_CO": "0.564"
  },
  "tghopolu": {
    "Chinese": "大潭山（一般性）",
    "Portuguese": "Taipa Grande (Ambiental)",
    "English": "Taipa Grande (Ambient)",
    "DDTT": "2026060720",
    "CODE": "TG",
    "HE_SO2": "1.393",
    "HE_PM10": "9.000",
    "HE_O3": "59.517",
    "HE_PM2_5": "4.000",
    "HE_NO2": "7.102",
    "HE_CO": "0.439"
  },
  "cdhopolu": {
    "Chinese": "石排灣（一般性）",
    "Portuguese": "Seac Pai Van (Ambiental)",
    "English": "Seac Pai Van (Ambient)",
    "DDTT": "2026060720",
    "CODE": "CD",
    "HE_SO2": "3.734",
    "HE_PM10": "23.000",
    "HE_O3": "40.205",
    "HE_PM2_5": "11.000",
    "HE_NO2": "12.535",
    "HE_CO": "0.336"
  }
}