{
  "datetime": "2026-06-22 18:45",
  "pohopolu": {
    "Chinese": "荷蘭園（路邊）",
    "Portuguese": "Conselheiro Ferreira de Almeida (Berma da Estrada)",
    "English": "Conselheiro Ferreira de Almeida (Roadside)",
    "DDTT": "2026062218",
    "CODE": "PO",
    "HE_PM10": "22.000",
    "HE_CO": "0.584",
    "HE_NO2": "34.136",
    "HE_PM2_5": "6.000",
    "HE_SO2": "4.813",
    "HE_O3": "28.990"
  },
  "khhopolu": {
    "Chinese": "九澳（路邊）",
    "Portuguese": "Ka-Hó (Berma da Estrada)",
    "English": "Ka-Hó (Roadside)",
    "DDTT": "2026062218",
    "CODE": "KH",
    "HE_PM10": "20.000",
    "HE_CO": "0.579",
    "HE_NO2": "9.380",
    "HE_PM2_5": "11.000",
    "HE_SO2": "4.116",
    "HE_O3": "41.963"
  },
  "enhopolu": {
    "Chinese": "台山（高密度住宅區）",
    "Portuguese": "Bairro de Tamagnini Barbosa (Alta Densidade Habitacional)",
    "English": "Bairro de Tamagnini Barbosa (High Density Residental Area)",
    "DDTT": "2026062218",
    "CODE": "EN",
    "HE_PM10": "22.000",
    "HE_CO": "0.705",
    "HE_NO2": "32.994",
    "HE_PM2_5": "4.000",
    "HE_SO2": "4.023",
    "HE_O3": "29.009"
  },
  "tchopolu": {
    "Chinese": "氹仔中心區（高密度住宅區）",
    "Portuguese": "Baixa da Taipa (Alta Densidade Habitacional)",
    "English": "Baixa da Taipa (High Density Residental Area)",
    "DDTT": "2026062218",
    "CODE": "TC",
    "HE_PM10": "18.000",
    "HE_CO": "0.473",
    "HE_NO2": "17.399",
    "HE_PM2_5": "7.000",
    "HE_SO2": "4.965",
    "HE_O3": "43.380"
  },
  "tghopolu": {
    "Chinese": "大潭山（一般性）",
    "Portuguese": "Taipa Grande (Ambiental)",
    "English": "Taipa Grande (Ambient)",
    "DDTT": "2026062218",
    "CODE": "TG",
    "HE_PM10": "14.000",
    "HE_CO": "0.404",
    "HE_NO2": "6.817",
    "HE_PM2_5": "6.000",
    "HE_SO2": "0.771",
    "HE_O3": "51.265"
  },
  "cdhopolu": {
    "Chinese": "石排灣（一般性）",
    "Portuguese": "Seac Pai Van (Ambiental)",
    "English": "Seac Pai Van (Ambient)",
    "DDTT": "2026062218",
    "CODE": "CD",
    "HE_PM10": "19.000",
    "HE_CO": "0.625",
    "HE_NO2": "10.057",
    "HE_PM2_5": "5.000",
    "HE_SO2": "2.007",
    "HE_O3": "48.989"
  }
}